nnff/__init__.py
nnff/nnff.py
nnff/nnff0.1.py
nnff-0.2.3.dist-info/METADATA
nnff-0.2.3.dist-info/WHEEL
nnff-0.2.3.dist-info/entry_points.txt
nnff-0.2.3.dist-info/top_level.txt
nnff-0.2.3.dist-info/RECORD
