Metadata-Version: 2.1
Name: nnff
Version: 0.2.3
Summary: An neutral network file framwork.
Home-page: https://github.com/lzfshub/nnfileframe.git
Author: LiuZhifei
Author-email: lzfsmail@gmail.com
License: MIT Licence
Keywords: pip,nnff,framework
Platform: win
Requires-Dist: gitpython
Requires-Dist: docopt
